tool_directory/__init__.py
tool_directory/exceptions.py
tool_directory/loader.py
tool_directory/model.py
tool_directory/prompt.py
tool_directory/utils.py
pytool_directory-0.0.2.dist-info/LICENSE
pytool_directory-0.0.2.dist-info/METADATA
pytool_directory-0.0.2.dist-info/WHEEL
pytool_directory-0.0.2.dist-info/top_level.txt
pytool_directory-0.0.2.dist-info/RECORD
