Metadata-Version: 2.1
Name: pytool-directory
Version: 0.0.2
Summary: Python package to create langchain tool from the Tool Directory For LangChain.
Author: Sheile
License: MIT
Project-URL: Homepage, https://github.com/dialogplay/pytool-directory
Project-URL: Bug Tracker, https://github.com/dialogplay/pytool-directory/issues
Project-URL: Source, https://github.com/dialogplay/pytool-directory
Keywords: langchain,gpt,dialogplay
Classifier: Programming Language :: Python :: 3
Classifier: License :: OSI Approved :: MIT License
Requires-Python: >=3.9
License-File: LICENSE
Requires-Dist: pydantic
Requires-Dist: requests
Requires-Dist: openai
Requires-Dist: langchain
Requires-Dist: PyYAML
Provides-Extra: dev
Requires-Dist: pre-commit ; extra == 'dev'
Requires-Dist: flake8 ; extra == 'dev'
Requires-Dist: pyproject-flake8 ; extra == 'dev'
Requires-Dist: flake8-quotes ; extra == 'dev'
Requires-Dist: pytest ; extra == 'dev'
Requires-Dist: pytest-cov ; extra == 'dev'
Requires-Dist: pytest-describe ; extra == 'dev'
Requires-Dist: pytest-watcher ; extra == 'dev'
Requires-Dist: requests-mock ; extra == 'dev'
